{
    "m_Version": 12,
    "DisplayName": "BTRX CLOTHING",
    "Icon": "Deliver",
    "Color": "FBFCFEFF",
    "IsExchange": 0,
    "InitStockPercent": 75.0,
  "Items": [
    {
      "ClassName": "BRTX_Operatorshirt_Camo21",
      "MaxPriceThreshold": 20000,
      "MinPriceThreshold": 10000,
      "SellPricePercent": -1.0,
      "MaxStockThreshold": 100,
      "MinStockThreshold": 1,
      "QuantityPercent": -1,
      "SpawnAttachments": [],
      "Variants": [
        "BRTX_Operatorshirt_Camo21A",
        "BRTX_Operatorshirt_Camo33",
        "BRTX_Operatorshirt_Camo33A",
        "BRTX_Operatorshirt_Camo34",
        "BRTX_Operatorshirt_Camo34A",
        "BRTX_Operatorshirt_Camo40",
        "BRTX_Operatorshirt_Camo40A",
        "BRTX_Operatorshirt_Camo45",
        "BRTX_Operatorshirt_Camo45A",
        "BRTX_Operatorshirt_Camo48",
        "BRTX_Operatorshirt_Camo48A",
        "BRTX_Operatorshirt_Camo49",
        "BRTX_Operatorshirt_Camo49A",
        "BRTX_Operatorshirt_Camo53",
        "BRTX_Operatorshirt_Camo53A",
        "BRTX_Operatorshirt_Camo56",
        "BRTX_Operatorshirt_Camo56A",
        "BRTX_Operatorshirt_Camo65",
        "BRTX_Operatorshirt_Camo65A",
        "BRTX_Operatorshirt_Camo77",
        "BRTX_Operatorshirt_Camo77A",
        "BRTX_Operatorshirt_Camo77_1",
        "BRTX_Operatorshirt_Camo77_1A",
        "BRTX_Operatorshirt_Camo101",
        "BRTX_Operatorshirt_Camo101A",
        "BRTX_Operatorshirt_Camo109",
        "BRTX_Operatorshirt_Camo109A",
        "BRTX_Operatorshirt_Camo111",
        "BRTX_Operatorshirt_Camo111A",
        "BRTX_Operatorshirt_Camo253",
        "BRTX_Operatorshirt_Camo253A",
        "BRTX_Operatorshirt_Camo256",
        "BRTX_Operatorshirt_Camo256A",
        "BRTX_Operatorshirt_Camo257",
        "BRTX_Operatorshirt_Camo257A",
        "BRTX_Operatorshirt_Camo257_1",
        "BRTX_Operatorshirt_Camo257_1A",
        "BRTX_Operatorshirt_Camo258",
        "BRTX_Operatorshirt_Camo258A",
        "BRTX_Operatorshirt_Camo264",
        "BRTX_Operatorshirt_Camo264A"
      ]
    },
    {
      "ClassName": "BRTX_Operatorshirt_Evil",
      "MaxPriceThreshold": 30000,
      "MinPriceThreshold": 15000,
      "SellPricePercent": -1.0,
      "MaxStockThreshold": 100,
      "MinStockThreshold": 1,
      "QuantityPercent": -1,
      "SpawnAttachments": [],
      "Variants": []
	},
    {
      "ClassName": "BRTX_Operatorshirt_BasicBlack",
      "MaxPriceThreshold": 30000,
      "MinPriceThreshold": 15000,
      "SellPricePercent": -1.0,
      "MaxStockThreshold": 100,
      "MinStockThreshold": 1,
      "QuantityPercent": -1,
      "SpawnAttachments": [],
      "Variants": [ ]
	},
    {
      "ClassName": "BRTX_Operatorshirt_Vanta",
      "MaxPriceThreshold": 30000,
      "MinPriceThreshold": 15000,
      "SellPricePercent": -1.0,
      "MaxStockThreshold": 100,
      "MinStockThreshold": 1,
      "QuantityPercent": -1,
      "SpawnAttachments": [],
      "Variants": []  
    },
    {
      "ClassName": "BRTX_Operatorshirt_Obsidian",
      "MaxPriceThreshold": 36000,
      "MinPriceThreshold": 18000,
      "SellPricePercent": -1.0,
      "MaxStockThreshold": 100,
      "MinStockThreshold": 1,
      "QuantityPercent": -1,
      "SpawnAttachments": [],
      "Variants": [
        "BRTX_Operatorshirt_Obsidian_1"
      ]
    },
    {
      "ClassName": "BRTX_combatpants_Camo15",
      "MaxPriceThreshold": 36000,
      "MinPriceThreshold": 18000,
      "SellPricePercent": -1.0,
      "MaxStockThreshold": 100,
      "MinStockThreshold": 1,
      "QuantityPercent": -1,
      "SpawnAttachments": [],
      "Variants": [
        "BRTX_combatpants_Camo15A",
        "BRTX_combatpants_Camo16_1",
        "BRTX_combatpants_Camo21",
        "BRTX_combatpants_Camo21A",
        "BRTX_combatpants_Camo33",
        "BRTX_combatpants_Camo33A",
        "BRTX_combatpants_Camo34",
        "BRTX_combatpants_Camo34A",
        "BRTX_combatpants_Camo40",
        "BRTX_combatpants_Camo40A",
        "BRTX_combatpants_Camo45",
        "BRTX_combatpants_Camo45A",
        "BRTX_combatpants_Camo48",
        "BRTX_combatpants_Camo48A",
        "BRTX_combatpants_Camo49",
        "BRTX_combatpants_Camo49A",
        "BRTX_combatpants_Camo53",
        "BRTX_combatpants_Camo53A",
        "BRTX_combatpants_Camo56",
        "BRTX_combatpants_Camo56A",
        "BRTX_combatpants_Camo65",
        "BRTX_combatpants_Camo65A",
        "BRTX_combatpants_Camo77",
        "BRTX_combatpants_Camo77A",
        "BRTX_combatpants_Camo77_1",
        "BRTX_combatpants_Camo77_1A",
        "BRTX_combatpants_Camo101",
        "BRTX_combatpants_Camo101A",
        "BRTX_combatpants_Camo109",
        "BRTX_combatpants_Camo109A",
        "BRTX_combatpants_Camo111",
        "BRTX_combatpants_Camo111A",
        "BRTX_combatpants_Camo253",
        "BRTX_combatpants_Camo253A",
        "BRTX_combatpants_Camo256",
        "BRTX_combatpants_Camo256A",
        "BRTX_combatpants_Camo257",
        "BRTX_combatpants_Camo257A",
        "BRTX_combatpants_Camo258",
        "BRTX_combatpants_Camo258A",
        "BRTX_combatpants_Camo264",
        "BRTX_combatpants_Camo264A"
      ]
    },
    {
      "ClassName": "BRTX_combatpants_Evil",
      "MaxPriceThreshold": 38000,
      "MinPriceThreshold": 19000,
      "SellPricePercent": -1.0,
      "MaxStockThreshold": 100,
      "MinStockThreshold": 1,
      "QuantityPercent": -1,
      "SpawnAttachments": [],
      "Variants": []
    },
    {
      "ClassName": "BRTX_combatpants_Obsidian",
      "MaxPriceThreshold": 38000,
      "MinPriceThreshold": 19000,
      "SellPricePercent": -1.0,
      "MaxStockThreshold": 100,
      "MinStockThreshold": 1,
      "QuantityPercent": -1,
      "SpawnAttachments": [],
      "Variants": []
    },
    {
      "ClassName": "BRTX_combatpants_BaseBlack",
      "MaxPriceThreshold": 40000,
      "MinPriceThreshold": 20000,
      "SellPricePercent": -1.0,
      "MaxStockThreshold": 100,
      "MinStockThreshold": 1,
      "QuantityPercent": -1,
      "SpawnAttachments": [],
      "Variants": []
    },
    {
      "ClassName": "BRTX_combatpants_Vanta",
      "MaxPriceThreshold": 40000,
      "MinPriceThreshold": 20000,
      "SellPricePercent": -1.0,
      "MaxStockThreshold": 100,
      "MinStockThreshold": 1,
      "QuantityPercent": -1,
      "SpawnAttachments": [],
      "Variants": []
    }
  ]
}